<annotation>
	<folder>n13001930</folder>
	<filename>n13001930_3750</filename>
	<source>
		<database>ImageNet database</database>
	</source>
	<size>
		<width>540</width>
		<height>477</height>
		<depth>3</depth>
	</size>
	<segmented>0</segmented>
	<object>
		<name>n13001930</name>
		<pose>Unspecified</pose>
		<truncated>0</truncated>
		<difficult>0</difficult>
		<bndbox>
			<xmin>259</xmin>
			<ymin>101</ymin>
			<xmax>524</xmax>
			<ymax>311</ymax>
		</bndbox>
	</object>
	<object>
		<name>n13001930</name>
		<pose>Unspecified</pose>
		<truncated>0</truncated>
		<difficult>0</difficult>
		<bndbox>
			<xmin>253</xmin>
			<ymin>287</ymin>
			<xmax>390</xmax>
			<ymax>444</ymax>
		</bndbox>
	</object>
	<object>
		<name>n13001930</name>
		<pose>Unspecified</pose>
		<truncated>0</truncated>
		<difficult>0</difficult>
		<bndbox>
			<xmin>9</xmin>
			<ymin>236</ymin>
			<xmax>198</xmax>
			<ymax>406</ymax>
		</bndbox>
	</object>
	<object>
		<name>n13001930</name>
		<pose>Unspecified</pose>
		<truncated>0</truncated>
		<difficult>0</difficult>
		<bndbox>
			<xmin>327</xmin>
			<ymin>43</ymin>
			<xmax>458</xmax>
			<ymax>115</ymax>
		</bndbox>
	</object>
	<object>
		<name>n13001930</name>
		<pose>Unspecified</pose>
		<truncated>0</truncated>
		<difficult>0</difficult>
		<bndbox>
			<xmin>109</xmin>
			<ymin>148</ymin>
			<xmax>271</xmax>
			<ymax>344</ymax>
		</bndbox>
	</object>
</annotation>